pyimager/__init__.py
pyimager/__main__.py
pyimager/compressing.py
pyimager/data.py
pyimager/designer.py
pyimager/displaying.py
pyimager/message.py
pyimager/utils.py
pyimager-3.4.8.dist-info/licenses/LICENSE.txt
pyimager-3.4.8.dist-info/METADATA
pyimager-3.4.8.dist-info/WHEEL
pyimager-3.4.8.dist-info/top_level.txt
pyimager-3.4.8.dist-info/RECORD
