Metadata-Version: 2.4
Name: pyimager
Version: 3.4.8
Summary: display images in console or compress them
Author-email: Leander Kafemann <leander@kafemann.berlin>
Project-URL: Homepage, https://github.com/LeanderKafemann/pyimager
Classifier: Programming Language :: Python :: 3
Classifier: License :: OSI Approved :: MIT License
Classifier: Operating System :: OS Independent
Requires-Python: >=3.11
License-File: LICENSE.txt
Requires-Dist: pycols
Requires-Dist: colorama
Dynamic: license-file
